{
  "title": "CTM360 HackerView Connector",
  "slug": "ctm360-hackerview",
  "description": "External import connector for CTM360 HackerView External Attack Surface Management platform. Imports security issues, resolved issues, domain assets, hostname assets, and IP address assets.",
  "short_description": "Import CTM360 HackerView attack surface management data",
  "logo": "external-import/ctm360-hackerview-feed/__metadata__/logo.png",
  "use_cases": [
    "Threat Intelligence"
  ],
  "verified": false,
  "last_verified_date": null,
  "playbook_supported": false,
  "max_confidence_level": 50,
  "support_version": ">=7.260529.0",
  "subscription_link": null,
  "source_code": "https://github.com/OpenCTI-Platform/connectors/tree/master/external-import/ctm360-hackerview-feed",
  "manager_supported": false,
  "container_version": "rolling",
  "container_image": "opencti/connector-ctm360-hackerview",
  "container_type": "EXTERNAL_IMPORT",
  "egress": [
    "hackerview.ctm360.com"
  ],
  "egress_config_keys": [
    "CTM360_HACKERVIEW_FEED_API_BASE_URL"
  ]
}
