{
  "$schema": "https://json-schema.org/draft/2020-12/schema",
  "$id": "https://www.filigran.io/connectors/redpanda_config.schema.json",
  "type": "object",
  "properties": {
    "OPENCTI_URL": {
      "description": "The base URL of the OpenCTI instance.",
      "format": "uri",
      "maxLength": 2083,
      "minLength": 1,
      "type": "string"
    },
    "OPENCTI_TOKEN": {
      "description": "The API token to connect to OpenCTI.",
      "type": "string"
    },
    "CONNECTOR_NAME": {
      "default": "Redpanda",
      "description": "The name of the connector.",
      "type": "string"
    },
    "CONNECTOR_SCOPE": {
      "default": [
        "redpanda"
      ],
      "description": "The scope of the connector, used to filter the live stream events.",
      "items": {
        "type": "string"
      },
      "type": "array"
    },
    "CONNECTOR_LOG_LEVEL": {
      "default": "error",
      "description": "The minimum level of logs to display.",
      "enum": [
        "debug",
        "info",
        "warn",
        "warning",
        "error"
      ],
      "type": "string"
    },
    "CONNECTOR_TYPE": {
      "const": "STREAM",
      "default": "STREAM",
      "type": "string"
    },
    "CONNECTOR_LIVE_STREAM_ID": {
      "description": "The ID of the OpenCTI live stream to connect to.",
      "type": "string"
    },
    "CONNECTOR_LIVE_STREAM_LISTEN_DELETE": {
      "default": true,
      "description": "Whether to listen for delete events on the live stream.",
      "type": "boolean"
    },
    "CONNECTOR_LIVE_STREAM_NO_DEPENDENCIES": {
      "default": true,
      "description": "Whether to ignore dependencies when processing events from the live stream.",
      "type": "boolean"
    },
    "REDPANDA_HTTP_PROXY_URL": {
      "description": "Base URL of the Redpanda HTTP Proxy / Pandaproxy (e.g. http://redpanda:8082).",
      "format": "uri",
      "maxLength": 2083,
      "minLength": 1,
      "type": "string"
    },
    "REDPANDA_TOPIC": {
      "default": "opencti",
      "description": "Redpanda topic that receives the OpenCTI stream events.",
      "type": "string"
    },
    "REDPANDA_USERNAME": {
      "default": "",
      "description": "Optional user name for HTTP basic authentication against the proxy.",
      "type": "string"
    },
    "REDPANDA_PASSWORD": {
      "default": "",
      "description": "Optional password for HTTP basic authentication against the proxy.",
      "format": "password",
      "type": "string",
      "writeOnly": true
    },
    "REDPANDA_SSL_VERIFY": {
      "default": true,
      "description": "Whether to verify the SSL certificate of the Redpanda HTTP Proxy.",
      "type": "boolean"
    }
  },
  "required": [
    "OPENCTI_URL",
    "OPENCTI_TOKEN",
    "CONNECTOR_LIVE_STREAM_ID",
    "REDPANDA_HTTP_PROXY_URL"
  ],
  "additionalProperties": true
}